pynof/__init__.py
pynof/energy.py
pynof/guess.py
pynof/input.py
pynof/integrals.py
pynof/minimization.py
pynof/optimization.py
pynof/output.py
pynof/parameters.py
pynof/pnof.py
pynof/postpnof.py
pynof/projection.py
pynof/utils.py
pynof-1.4.dist-info/METADATA
pynof-1.4.dist-info/WHEEL
pynof-1.4.dist-info/licenses/LICENSE
pynof-1.4.dist-info/RECORD
