Metadata-Version: 2.4
Name: pynof
Version: 1.4
Summary: Package for performing Piris Natural Orbital Functionals (PNOF)
Project-URL: Homepage, https://github.com/felipelewyee/PyNOF
Author-email: Juan Felipe Huan Lew Yee <felipe.lew.yee@gmail.com>
License-File: LICENSE
Classifier: License :: OSI Approved :: GNU General Public License v3 (GPLv3)
Classifier: Operating System :: OS Independent
Classifier: Programming Language :: Python :: 3
Requires-Python: >=3.8
Requires-Dist: numba
Requires-Dist: numpy
Requires-Dist: scipy
